fpc/__init__.py
fpc/connector.py
fpc/connectorconf.py
fpc/subscribing_tool.py
fiware_pyspark_connector-0.0.10.dist-info/LICENSE.txt
fiware_pyspark_connector-0.0.10.dist-info/METADATA
fiware_pyspark_connector-0.0.10.dist-info/WHEEL
fiware_pyspark_connector-0.0.10.dist-info/top_level.txt
fiware_pyspark_connector-0.0.10.dist-info/RECORD
