Metadata-Version: 2.1
Name: fiware-pyspark-connector
Version: 0.0.10
Summary: Connects FIWARE Context Brokers with fiware_pyspark_connector
Home-page: https://github.com/Engineering-Research-and-Development/fiware-orion-pyspark-connector
Author: Emilio Cimino
Author-email: emilio.cimino@outlook.it
License: "AGPL-3.0-only"
Classifier: Programming Language :: Python :: 3
Classifier: Operating System :: OS Independent
License-File: LICENSE.txt
Requires-Dist: py4j (==0.10.9.3)
Requires-Dist: pyspark (==3.2.1)
Requires-Dist: requests
Requires-Dist: psutil
